esp_flasher/__init__.py
esp_flasher/__main__.py
esp_flasher/common.py
esp_flasher/const.py
esp_flasher/gui.py
esp_flasher/helpers.py
esp_flasher/own_esptool.py
esp_flasher-3.2.0.dist-info/licenses/LICENSE
esp_flasher-3.2.0.dist-info/METADATA
esp_flasher-3.2.0.dist-info/WHEEL
esp_flasher-3.2.0.dist-info/entry_points.txt
esp_flasher-3.2.0.dist-info/top_level.txt
esp_flasher-3.2.0.dist-info/RECORD
