Metadata-Version: 2.4
Name: esp_flasher
Version: 3.2.0
Summary: ESP8266/ESP32 Tasmota firmware flasher for ESP
Home-page: https://github.com/Jason2866/ESP_Flasher
Author: Jason2866
Author-email: obermeier.johann@googlemail.com
License: MIT
Keywords: home,automation
Platform: any
Requires-Python: >=3.8,<4.0
License-File: LICENSE
Requires-Dist: pyserial>=3.5
Requires-Dist: requests<3,>=2.24.0
Requires-Dist: PyQT5>=5.15.10
Requires-Dist: distro>=1.9.0
Dynamic: author
Dynamic: author-email
Dynamic: description
Dynamic: description-content-type
Dynamic: home-page
Dynamic: keywords
Dynamic: license
Dynamic: license-file
Dynamic: platform
Dynamic: requires-dist
Dynamic: requires-python
Dynamic: summary
